eyespider/__init__.py
eyespider/downloader.py
eyespider/field.py
eyespider/item.py
eyespider/spider.py
eyespider/utils/__init__.py
eyespider/utils/function.py
eyespider/utils/log.py
eyespider/utils/user_agents.txt
eyespider-1.0.1.dist-info/DESCRIPTION.rst
eyespider-1.0.1.dist-info/METADATA
eyespider-1.0.1.dist-info/RECORD
eyespider-1.0.1.dist-info/WHEEL
eyespider-1.0.1.dist-info/metadata.json
eyespider-1.0.1.dist-info/top_level.txt
