Metadata-Version: 2.0
Name: eyespider
Version: 1.0.1
Summary: A simple,qiuck scraping micro-framework
Home-page: https://github.com/BlueRagdoll/eyespider/blob/master/README.md
Author: Chuck Huang
Author-email: chuckhunagcm@gmail.com
License: UNKNOWN
Platform: UNKNOWN
Requires-Dist: lxml
Requires-Dist: requests
Requires-Dist: cchardet
Requires-Dist: cssselect
